pyLump.py
pylump-0.1.0.dist-info/METADATA
pylump-0.1.0.dist-info/WHEEL
pylump-0.1.0.dist-info/licenses/License
pylump-0.1.0.dist-info/RECORD
