Metadata-Version: 2.1
Name: pyLump
Version: 0.1.0
Summary: Multi Degree of Freedom (mass-spring-damper) Models.
Project-URL: homepage, https://github.com/ladisk/pyLump
Project-URL: documentation, https://pyLump.readthedocs.io/en/latest/
Project-URL: source, https://github.com/ladisk/pyLump
Author-email: "Luka Novak, Domen Gorjup, Janko Slavič" <janko.slavic@fs.uni-lj.si>
Maintainer-email: "Luka Novak, Domen Gorjup, Janko Slavič" <janko.slavic@fs.uni-lj.si>
License-Expression: MIT
License-File: License
Keywords: MDOF,dynamics,lumped mass
Classifier: Development Status :: 5 - Production/Stable
Classifier: Intended Audience :: Developers
Classifier: License :: OSI Approved :: MIT License
Classifier: Programming Language :: Python :: 3.10
Classifier: Topic :: Scientific/Engineering
Requires-Python: >=3.10
Requires-Dist: matplotlib
Requires-Dist: numpy>=1.11.0
Requires-Dist: py
Requires-Dist: pytest
Requires-Dist: scipy>=1.2.0
Provides-Extra: dev
Requires-Dist: jupyter; extra == 'dev'
Requires-Dist: nbconvert; extra == 'dev'
Requires-Dist: nbsphinx; extra == 'dev'
Requires-Dist: nbsphinx-link; extra == 'dev'
Requires-Dist: pytest; extra == 'dev'
Requires-Dist: sphinx; extra == 'dev'
Requires-Dist: sphinx-book-theme; extra == 'dev'
Requires-Dist: sphinx-rtd-theme; extra == 'dev'
Requires-Dist: twine; extra == 'dev'
Requires-Dist: wheel; extra == 'dev'
